{ "type": "FeatureCollection", "crs": { "type": "name", "properties": { "name": "urn:ogc:def:crs:OGC:1.3:CRS84" } }, "features": [ 
{ "type": "Feature", "properties": { "Name": "William Falk-Wallace", "Description": "Tue Nov  5 18:39:25 EST 2013; Location Accuracy: 65.000000" }, "geometry": { "type": "Point", "coordinates": [ -73.969707, 40.800835, 0.0 ] } },
{ "type": "Feature", "properties": { "Name": "William Falk-Wallace", "Description": "Tue Nov  5 18:36:41 EST 2013; Location Accuracy: 65.000000" }, "geometry": { "type": "Point", "coordinates": [ -73.969690, 40.800829, 0.0 ] } },
{ "type": "Feature", "properties": { "Name": "William Falk-Wallace", "Description": "Tue Nov  5 18:35:21 EST 2013; Location Accuracy: 65.000000" }, "geometry": { "type": "Point", "coordinates": [ -73.969655, 40.800808, 0.0 ] } },
{ "type": "Feature", "properties": { "Name": "William Falk-Wallace", "Description": "Tue Nov  5 18:28:04 EST 2013; Location Accuracy: 65.000000" }, "geometry": { "type": "Point", "coordinates": [ -73.969644, 40.800805, 0.0 ] } },
{ "type": "Feature", "properties": { "Name": "William Falk-Wallace", "Description": "Wed Oct 16 17:28:40 EDT 2013; Location Accuracy: 65.000000" }, "geometry": { "type": "Point", "coordinates": [ -73.960970, 40.809180, 0.0 ] } },
{ "type": "Feature", "properties": { "Name": "William Falk-Wallace", "Description": "Tue Oct  8 10:30:17 EDT 2013; Location Accuracy: 99.341928" }, "geometry": { "type": "Point", "coordinates": [ -73.962591, 40.809815, 0.0 ] } },
{ "type": "Feature", "properties": { "Name": "William Falk-Wallace", "Description": "Tue Oct  8 00:37:39 EDT 2013; Location Accuracy: 65.000000" }, "geometry": { "type": "Point", "coordinates": [ -73.969743, 40.800863, 0.0 ] } },
{ "type": "Feature", "properties": { "Name": "William Falk-Wallace", "Description": "Mon Oct  7 12:07:26 EDT 2013; Location Accuracy: 65.000000" }, "geometry": { "type": "Point", "coordinates": [ -73.961557, 40.808922, 0.0 ] } },
{ "type": "Feature", "properties": { "Name": "William Falk-Wallace", "Description": "Sun Sep 29 15:15:56 EDT 2013; Location Accuracy: 65.000000" }, "geometry": { "type": "Point", "coordinates": [ -73.961282, 40.809388, 0.0 ] } },
{ "type": "Feature", "properties": { "Name": "William Falk-Wallace", "Description": "Sun Sep 29 12:54:07 EDT 2013; Location Accuracy: 65.000000" }, "geometry": { "type": "Point", "coordinates": [ -73.961242, 40.809360, 0.0 ] } },
{ "type": "Feature", "properties": { "Name": "William Falk-Wallace", "Description": "Mon Sep 23 10:54:50 EDT 2013; Location Accuracy: 65.000000" }, "geometry": { "type": "Point", "coordinates": [ -73.961300, 40.809397, 0.0 ] } },
{ "type": "Feature", "properties": { "Name": "William Falk-Wallace", "Description": "Fri Sep 20 18:45:43 EDT 2013; Location Accuracy: 65.000000" }, "geometry": { "type": "Point", "coordinates": [ -73.967201, 40.793135, 0.0 ] } },
{ "type": "Feature", "properties": { "Name": "William Falk-Wallace", "Description": "Fri Sep 20 18:45:14 EDT 2013; Location Accuracy: 65.000000" }, "geometry": { "type": "Point", "coordinates": [ -73.967201, 40.793135, 0.0 ] } },
{ "type": "Feature", "properties": { "Name": "William Falk-Wallace", "Description": "Thu Sep 19 15:55:14 EDT 2013; Location Accuracy: 65.000000" }, "geometry": { "type": "Point", "coordinates": [ -73.959675, 40.809082, 0.0 ] } },
{ "type": "Feature", "properties": { "Name": "William Falk-Wallace", "Description": "Thu Sep 19 15:54:50 EDT 2013; Location Accuracy: 65.000000" }, "geometry": { "type": "Point", "coordinates": [ -73.959712, 40.809083, 0.0 ] } }
]}
